draw_rna/__init__.py
draw_rna/draw.py
draw_rna/draw_all.py
draw_rna/draw_from_rdat.py
draw_rna/draw_utils.py
draw_rna/inv_utils.py
draw_rna/ipynb_draw.py
draw_rna/mpl.py
draw_rna/render_rna.py
draw_rna/svg.py
draw_rna-0.4.3.dist-info/licenses/LICENSE
draw_rna-0.4.3.dist-info/METADATA
draw_rna-0.4.3.dist-info/WHEEL
draw_rna-0.4.3.dist-info/top_level.txt
draw_rna-0.4.3.dist-info/RECORD
