Metadata-Version: 2.4
Name: draw_rna
Version: 0.4.3
Summary: Draw RNA secondary structures in Python
Author-email: Eternagame <support@eternagame.org>
Project-URL: Homepage, https://github.com/eternagame/draw_rna
Project-URL: Bug Tracker, https://github.com/eternagame/draw_rna/issues
Classifier: Programming Language :: Python :: 3
Classifier: License :: OSI Approved :: MIT License
Classifier: Operating System :: OS Independent
Requires-Python: >=3.7
License-File: LICENSE
Requires-Dist: argparse>=1.4
Requires-Dist: numpy>=1.15
Requires-Dist: matplotlib>=3.2
Requires-Dist: rdat-kit>=1.6
Dynamic: license-file
